Workbook
Name \0: #REF!
Name \0: #REF!
Name \0: #REF!
Name \0: #REF!
Name \a: #REF!
Name \a: #REF!
Name \a: #REF!
Name \a: #REF!
Name \CA: #REF!
Name \CA: #REF!
Name \CO: #REF!
Name \CO: #REF!
Name \Convergence: 1.79769313486231E+59
Name \d: #REF!
Name \d: #REF!
Name \d: #REF!
Name \d: #REF!
Name \e: #REF!
Name \e: #REF!
Name \e: #REF!
Name \e: #REF!
Name \f: #REF!
Name \f: #REF!
Name \f: #REF!
Name \f: #REF!
Name \g: #REF!
Name \g: #REF!
Name \h: #REF!
Name \h: #REF!
Name \I: #REF!
Name \I: #REF!
Name \IterationCount: 0
Name \m: #REF!
Name \m: #REF!
Name \p: #REF!
Name \p: #REF!
Name \R: #REF!
Name \R: #REF!
Name \s: #REF!
Name \s: #REF!
Name \t: #REF!
Name \t: #REF!
Name \u: #REF!
Name \u: #REF!
Name \W: #REF!
Name \W: #REF!
Name \WorstStream: " "
Name \y: #REF!
Name \y: #REF!
Name \y: #REF!
Name \y: #REF!
Name _____T2: #REF!
Name _____T2: #REF!
Name _____T2: #REF!
Name _____T2: #REF!
Name ____aux10: #REF!
Name ____aux10: #REF!
Name ____aux10: #REF!
Name ____aux10: #REF!
Name ____aux3: #REF!

Sheet Baseline BoQ
A1: Section | B1: Bill No. | C1: Materials Code | D1: Item No. | E1: Pay Ref | F1: Description | G1: Unit | H1: Contract Quantity | I1: Contract Rate | J1: Contract Amount | K1: 1
A2: Section 1 Preliminaries | B2: Bill No. 1: Fixed Charge Items | F2: SECTION NO. 1
A3: Section 1 Preliminaries | B3: Bill No. 1: Fixed Charge Items | E3: SANS 1200A | F3: PRELIMINARY AND GENERAL
A4: Section 1 Preliminaries | B4: Bill No. 1: Fixed Charge Items | F4: (Applicable to the whole of the Works)
A5: Section 1 Preliminaries | B5: Bill No. 1: Fixed Charge Items | F5: BILL NO. 1
A6: Section 1 Preliminaries | B6: Bill No. 1: Fixed Charge Items | E6: 8.3 | F6: FIXED CHARGE ITEMS
A7: Section 1 Preliminaries | B7: Bill No. 1: Fixed Charge Items | F7: PREAMBLE
A8: Section 1 Preliminaries | B8: Bill No. 1: Fixed Charge Items | F8: A detailed breakdown of the Preliminaries and General costs should be submitted with this tender
A9: Section 1 Preliminaries | B9: Bill No. 1: Fixed Charge Items | D9: A | E9: 8.3.1 | F9: Contractual requirements | G9: SUM | H9: 1 | I9: 500000 | J9: =H9*I9 -> 500000
A10: Section 1 Preliminaries | B10: Bill No. 1: Fixed Charge Items | E10: 8.3.2.2 | F10: Facilities for Contractor
A11: Section 1 Preliminaries | B11: Bill No. 1: Fixed Charge Items | D11: B | E11: 8.3.2.2.a) | F11: Offices and storage sheds | G11: SUM | H11: 1 | I11: 30000 | J11: =H11*I11 -> 30000
A12: Section 1 Preliminaries | B12: Bill No. 1: Fixed Charge Items | D12: C | E12: 8.3.2.2.b) | F12: Workshops | G12: SUM | H12: 1 | I12: 10000 | J12: =H12*I12 -> 10000
A13: Section 1 Preliminaries | B13: Bill No. 1: Fixed Charge Items | D13: D | E13: 8.3.2.2.c) | F13: Laboratories. | G13: Sum | H13: 1 | I13: 10000 | J13: =I13*H13 -> 10000
A14: Section 1 Preliminaries | B14: Bill No. 1: Fixed Charge Items | D14: E | E14: 8.3.2.2.d) | F14: Living accommodation. | G14: Sum | H14: 1 | I14: 20000 | J14: =I14*H14 -> 20000
A15: Section 1 Preliminaries | B15: Bill No. 1: Fixed Charge Items | D15: F | E15: 8.3.2.2.e) | F15: Ablution and latrine facilities. | G15: Sum | H15: 1 | I15: 20000 | J15: =I15*H15 -> 20000
A16: Section 1 Preliminaries | B16: Bill No. 1: Fixed Charge Items | D16: G | E16: 8.3.2.2.f) | F16: Tools and equipment | G16: SUM | H16: 1 | I16: 20000 | J16: =H16*I16 -> 20000
A17: Section 1 Preliminaries | B17: Bill No. 1: Fixed Charge Items | D17: H | E17: 8.3.2.2.g) | F17: Water supplies, electric power, communications, dealing with water, and access | G17: SUM | H17: 1 | I17: 15000 | J17: =H17*I17 -> 15000
A18: Section 1 Preliminaries | B18: Bill No. 1: Fixed Charge Items | D18: J | E18: 8.3.2.2.j) | F18: Plant. | G18: SUM | H18: 1 | I18: 25000 | J18: =I18*H18 -> 25000
A19: Section 1 Preliminaries | B19: Bill No. 1: Fixed Charge Items | D19: K | F19: Medicals and inductions | G19: SUM | H19: 1 | I19: 20000 | J19: =I19*H19 -> 20000
A20: Section 1 Preliminaries | B20: Bill No. 1: Fixed Charge Items | D20: L | F20: Fencing of laydown area | G20: SUM | H20: 1 | I20: 55933.13 | J20: =I20*H20 -> 55933.13
A21: Section 1 Preliminaries | B21: Bill No. 1: Fixed Charge Items | D21: M | E21: 8.3.3 | F21: Other fixed charge obligations | G21: SUM | H21: 1 | I21: 5000 | J21: =H21*I21 -> 5000
A22: Section 1 Preliminaries | B22: Bill No. 1: Fixed Charge Items | D22: N | E22: 8.3.4 | F22: Removal of site establishment | G22: SUM | H22: 1 | I22: 15000 | J22: =H22*I22 -> 15000
A23: Section 1 Preliminaries | B23: Bill No. 2: Time Related Items | F23: SECTION NO. 1
A24: Section 1 Preliminaries | B24: Bill No. 2: Time Related Items | E24: SANS 1200A | F24: PRELIMINARY AND GENERAL
A25: Section 1 Preliminaries | B25: Bill No. 2: Time Related Items | F25: (Applicable to the whole of the Works)
A26: Section 1 Preliminaries | B26: Bill No. 2: Time Related Items | F26: BILL NO. 2
A27: Section 1 Preliminaries | B27: Bill No. 2: Time Related Items | E27: 8.4 | F27: TIME RELATED ITEMS
A28: Section 1 Preliminaries | B28: Bill No. 2: Time Related Items | F28: PREAMBLE
A29: Section 1 Preliminaries | B29: Bill No. 2: Time Related Items | F29: A detailed breakdown of the Preliminaries and General costs should be submitted with this tender
A30: Section 1 Preliminaries | B30: Bill No. 2: Time Related Items | D30: A | E30: 8.4.1 | F30: Contractual requirements | G30: SUM | H30: 1 | I30: 100000 | J30: =H30*I30 -> 100000
A31: Section 1 Preliminaries | B31: Bill No. 2: Time Related Items | E31: 8.4.2 | F31: Operation and Maintenance of Facilities on Site, for Duration of Construction, (unless otherwise stated)
A32: Section 1 Preliminaries | B32: Bill No. 2: Time Related Items | E32: 8.4.2.2 | F32: Facilities for Contractor
A33: Section 1 Preliminaries | B33: Bill No. 2: Time Related Items | D33: B | E33: 8.4.2.2.a) | F33: Offices and storage sheds | G33: SUM | H33: 1 | I33: 30000 | J33: =H33*I33 -> 30000
A34: Section 1 Preliminaries | B34: Bill No. 2: Time Related Items | D34: C | E34: 8.4.2.2.b) | F34: Workshops | G34: SUM | H34: 1 | I34: 15000 | J34: =H34*I34 -> 15000
A35: Section 1 Preliminaries | B35: Bill No. 2: Time Related Items | D35: D | E35: 8.4.2.2.c) | F35: Laboratories | G35: SUM | H35: 1 | I35: 15000 | J35: =H35*I35 -> 15000
A36: Section 1 Preliminaries | B36: Bill No. 2: Time Related Items | D36: E | E36: 8.4.2.2.d) | F36: Living accommodation | G36: SUM | H36: 1 | I36: 30000 | J36: =H36*I36 -> 30000
A37: Section 1 Preliminaries | B37: Bill No. 2: Time Related Items | D37: F | E37: 8.4.2.2.e) | F37: Ablution and latrine facilities | G37: SUM | H37: 1 | I37: 30000 | J37: =H37*I37 -> 30000
A38: Section 1 Preliminaries | B38: Bill No. 2: Time Related Items | D38: G | E38: 8.4.2.2.f) | F38: Tools and equipment | G38: SUM | H38: 1 | I38: 20000 | J38: =H38*I38 -> 20000
A39: Section 1 Preliminaries | B39: Bill No. 2: Time Related Items | D39: H | E39: 8.4.2.2.g) | F39: Water supplies, electric power, communications, dealing with water, and access | G39: SUM | H39: 1 | I39: 20000 | J39: =H39*I39 -> 20000
A40: Section 1 Preliminaries | B40: Bill No. 2: Time Related Items | D40: J | E40: 8.4.2.2.j) | F40: Plant | G40: SUM | H40: 1 | I40: 60000 | J40: =H40*I40 -> 60000
A41: Section 1 Preliminaries | B41: Bill No. 2: Time Related Items | D41: K | E41: 8.4.3 | F41: Supervision for duration of construction | G41: SUM | H41: 1 | I41: 120000 | J41: =H41*I41 -> 120000
A42: Section 1 Preliminaries | B42: Bill No. 2: Time Related Items | D42: L | E42: 8.4.4 | F42: Company and head office overhead costs for duration of the contract | G42: SUM | H42: 1 | I42: 24000 | J42: =H42*I42 -> 24000
A43: Section 1 Preliminaries | B43: Bill No. 2: Time Related Items | D43: M | F43: Safety Compliance | G43: Sum | H43: 1 | I43: 200000 | J43: =I43*H43 -> 200000
A44: Section 1 Preliminaries | B44: Bill No. 2: Time Related Items | D44: N | E44: 8.4.5 | F44: Other time related obligations | G44: SUM | H44: 1 | I44: 10000 | J44: =H44*I44 -> 10000
A45: Section 1 Preliminaries | B45: Bill No. 2: Time Related Items | D45: P | E45: 8.4.5.1 | F45: Community Liason Officer's Salary | G45: SUM | H45: 1 | I45: 60000 | J45: =H45*I45 -> 60000
A46: Section 1 Preliminaries | B46: Bill No. 2: Time Related Items | D46: Q | E46: 8.4.5.2 | F46: Security for the duration of the project | G46: SUM | H46: 1 | I46: 100000 | J46: =H46*I46 -> 100000
A47: Section 2: Media Centre | B47: Bill No. 1: Earthworks | F47: SECTION NO. 2 | K47: 1
A48: Section 2: Media Centre | B48: Bill No. 1: Earthworks | F48: LEPHADIMISHA - MEDIA CENTRE | K48: 1
A49: Section 2: Media Centre | B49: Bill No. 1: Earthworks | F49: BILL NO. 1 | K49: 1
A50: Section 2: Media Centre | B50: Bill No. 1: Earthworks | E50: SANS 1200D | F50: EARTHWORKS | K50: 1
A51: Section 2: Media Centre | B51: Bill No. 1: Earthworks | F51: NOTES | K51: 1
A52: Section 2: Media Centre | B52: Bill No. 1: Earthworks | F52: For preambles see "Model Preambles for Trades 2017" | K52: 1
A53: Section 2: Media Centre | B53: Bill No. 1: Earthworks | F53: SUPPLEMENTARY PREAMBLES | K53: 1
A54: Section 2: Media Centre | B54: Bill No. 1: Earthworks | F54: Nature of ground | K54: 1
A55: Section 2: Media Centre | B55: Bill No. 1: Earthworks | F55: Descriptions of excavations shall be deemed to include all ground conditions classifiable as "earth", and where conditions of a more difficult character are indicated, these are separately measured. | K55: 1
A56: Section 2: Media Centre | B56: Bill No. 1: Earthworks | E56: 8.3 | F56: SCHEDULED ITEMS | K56: 1
A57: Section 2: Media Centre | B57: Bill No. 1: Earthworks | E57: 8.3.1 | F57: Site preparation | K57: 1
A58: Section 2: Media Centre | B58: Bill No. 1: Earthworks | D58: A | E58: 8.3.1.1 | F58: Rip and scarify in-situ 150mm layer free of organic material and compact to 93% Mod AASHTO density | G58: m2 | H58: 307 | I58: 25 | J58: =I58*H58 -> 7675 | K58: 1
A59: Section 2: Media Centre | B59: Bill No. 1: Earthworks | D59: B | E59: 8.3.1.2 | F59: Remove topsoil to nominal depth 150mm, stockpile and maintain | G59: m2 | H59: =H58 -> 307 | I59: 65 | J59: =I59*H59 -> 19955 | K59: 1
A60: Section 2: Media Centre | B60: Bill No. 1: Earthworks | F60: EXCAVATION, FILLING, ETC | K60: 1
A61: Section 2: Media Centre | B61: Bill No. 1: Earthworks | E61: 8.3.3 | F61: Restricted Excavation | K61: 1
A62: Section 2: Media Centre | B62: Bill No. 1: Earthworks | D62: C | E62: 8.3.3.a.1) | F62: Excavate for restricted footings in all materials | G62: m3 | H62: 112 | I62: 85 | J62: =H62*I62 -> 9520 | K62: 1
A63: Section 2: Media Centre | B63: Bill No. 1: Earthworks | F63: Extra-over for | K63: 1
A64: Section 2: Media Centre | B64: Bill No. 1: Earthworks | D64: D | E64: 8.3.3.b.1) | F64: Intermediate excavation | G64: m3 | H64: =H62*0.1 -> 11.2 | I64: 95 | J64: =H64*I64 -> 1064 | K64: 1
A65: Section 2: Media Centre | B65: Bill No. 1: Earthworks | D65: E | E65: 8.3.3.b.2) | F65: Hard rock excavation | G65: m3 | H65: =H62*0.05 -> 5.6 | I65: 350 | J65: =H65*I65 -> 1960 | K65: 1
A66: Section 2: Media Centre | B66: Bill No. 1: Earthworks | E66: 8.3.4 | F66: Importing of Material | K66: 1
A67: Section 2: Media Centre | B67: Bill No. 1: Earthworks | E67: 8.3.4.a) | F67: Extra-over for importation of materials from commercial sources | K67: 1
A68: Section 2: Media Centre | B68: Bill No. 1: Earthworks | D68: F | F68: G5 material compacted in 150mm thick layers to 95% MOD AASHTO density at 1% to 2% optimum moisture content under footing | G68: m3 | H68: 41 | I68: 320 | J68: =I68*H68 -> 13120 | K68: 1
A69: Section 2: Media Centre | B69: Bill No. 1: Earthworks | D69: G | F69: G5 Material in layers compacted to 95% Mod AASHTO density in layers not exceeding 150mm under surface bed | G69: m3 | H69: 99 | I69: 320 | J69: =I69*H69 -> 31680 | K69: 1
A70: Section 2: Media Centre | B70: Bill No. 1: Earthworks | D70: H | E70: 8.3.6 | F70: Overhaul | K70: 1
A71: Section 2: Media Centre | B71: Bill No. 1: Earthworks | D71: J | E71: 8.3.6.b) | F71: Long overhaul in excess of 2km and within a 20km radius | G71: m3.km | H71: =H62*12 -> 1344 | I71: 8 | J71: =I71*H71 -> 10752 | K71: 1
A72: Section 2: Media Centre | B72: Bill No. 1: Earthworks | F72: SOIL POISONING | K72: 1
A73: Section 2: Media Centre | B73: Bill No. 1: Earthworks | F73: Soil insecticide in accordance with SANS 5859 | K73: 1
A74: Section 2: Media Centre | B74: Bill No. 1: Earthworks | D74: K | F74: Under floors etc. including forming and poisoning shallow furrows against foundation walls etc., filling in furrows and ramming | G74: m2 | H74: 353 | I74: 35 | J74: =I74*H74 -> 12355 | K74: 1
A75: Section 2: Media Centre | B75: Bill No. 2: Concrete (Structural) | F75: SECTION NO. 2 | K75: 1
A76: Section 2: Media Centre | B76: Bill No. 2: Concrete (Structural) | F76: =F48 -> LEPHADIMISHA - MEDIA CENTRE | K76: 1
A77: Section 2: Media Centre | B77: Bill No. 2: Concrete (Structural) | F77: BILL NO. 2 | K77: 1
A78: Section 2: Media Centre | B78: Bill No. 2: Concrete (Structural) | E78: SANS 1200G | F78: CONCRETE (STRUCTURAL) | K78: 1
A79: Section 2: Media Centre | B79: Bill No. 2: Concrete (Structural) | F79: NOTES | K79: 1
A80: Section 2: Media Centre | B80: Bill No. 2: Concrete (Structural) | F80: For preambles see "Model Preambles for Trades 2017" | K80: 1
A81: Section 2: Media Centre | B81: Bill No. 2: Concrete (Structural) | F81: SUPPLEMENTARY PREAMBLES | K81: 1
A82: Section 2: Media Centre | B82: Bill No. 2: Concrete (Structural) | F82: Cost of tests | K82: 1
A83: Section 2: Media Centre | B83: Bill No. 2: Concrete (Structural) | F83: The costs of making, storing and testing of concrete test cubes as required under clause 7 "Tests" of SANS 1200G shall include the cost of providing cube moulds necessary for the purpose, for testing costs and for submitting reports on the tests to the Supervisor. The testing shall be undertaken by an independent firm or institution nominated by the contractor to the approval of the Supervisor. (Test cubes are measured separately) | K83: 1
A84: Section 2: Media Centre | B84: Bill No. 2: Concrete (Structural) | F84: Formwork | K84: 1
A85: Section 2: Media Centre | B85: Bill No. 2: Concrete (Structural) | F85: Formwork to soffits of solids etc. shall be deemed to be slabs not exceeding 300mm thick unless otherwise described | K85: 1
A86: Section 2: Media Centre | B86: Bill No. 2: Concrete (Structural) | F86: Formwork to sides of bases, pile caps, ground beams, etc. will only be measured where it is prescribed by the engineer for design reasons. Formwork necessitated by irregularity or collapse of excavated faces will not be measured and the cost thereof shall be deemed to be included in the allowance for taking the risk of collapse of the sides of the excavations, provision for which is made in "Earthworks" | K86: 1
A87: Section 2: Media Centre | B87: Bill No. 2: Concrete (Structural) | F87: All H.D bolts, washers and nuts to be supplied by the contractor | K87: 1
A88: Section 2: Media Centre | B88: Bill No. 2: Concrete (Structural) | F88: Rates to include for sandblasting and galvanizing all bolts and metal work to applicable specification | K88: 1
A89: Section 2: Media Centre | B89: Bill No. 2: Concrete (Structural) | E89: 8.2 | F89: FORMWORK (PROVISIONAL) | K89: 1
A90: Section 2: Media Centre | B90: Bill No. 2: Concrete (Structural) | E90: 8.2.1 | F90: Rough formwork | K90: 1
A91: Section 2: Media Centre | B91: Bill No. 2: Concrete (Structural) | D91: A | F91: To sides footing | G91: m2 | H91: 67 | I91: 385 | J91: =H91*I91 -> 25795 | K91: 1
A92: Section 2: Media Centre | B92: Bill No. 2: Concrete (Structural) | E92: 8.3 | F92: REINFORCEMENT (PROVISIONAL) | K92: 1
A93: Section 2: Media Centre | B93: Bill No. 2: Concrete (Structural) | E93: 8.3.1 | F93: Steel Bars in Structural Steel | K93: 1
A94: Section 2: Media Centre | B94: Bill No. 2: Concrete (Structural) | E94: 8.3.1 | F94: Steel Bars | K94: 1
A95: Section 2: Media Centre | B95: Bill No. 2: Concrete (Structural) | F95: High-tensile | K95: 1
A96: Section 2: Media Centre | B96: Bill No. 2: Concrete (Structural) | D96: B | F96: Various Bars | G96: t | H96: 0.539 | I96: 19500 | J96: =H96*I96 -> 10510.5 | K96: 1
A97: Section 2: Media Centre | B97: Bill No. 2: Concrete (Structural) | F97: Mild steel | K97: 1
A98: Section 2: Media Centre | B98: Bill No. 2: Concrete (Structural) | D98: C | F98: Various Bars | G98: t | H98: 0.12 | I98: 19500 | J98: =H98*I98 -> 2340 | K98: 1
A99: Section 2: Media Centre | B99: Bill No. 2: Concrete (Structural) | E99: 8.3.2 | F99: High-tensile welded mesh | K99: 1
A100: Section 2: Media Centre | B100: Bill No. 2: Concrete (Structural) | D100: D | F100: Ref 395 layer mesh in surface bed | G100: m2 | H100: 141 | I100: 145 | J100: =H100*I100 -> 20445 | K100: 1
...

Sheet Output BoQ
A1: Structure | B1: Bill No. | C1: Trade Code | D1: Accounts Code | E1: Specification Code | F1: Item No. | G1: Pay Ref | H1: Description | I1: Unit | J1: Contract Quantity | K1: Contract Rate | L1: Contract Amount | M1: Progress Quantity | N1: Forecast Quantity | O1: New Materials Rate | P1: Progress Amount | Q1: Forecast Amount
A2: Section 1 Preliminaries | B2: Bill No. 1: Fixed Charge Items | H2: SECTION NO. 1
A3: Section 1 Preliminaries | B3: Bill No. 1: Fixed Charge Items | G3: SANS 1200A | H3: PRELIMINARY AND GENERAL
A4: Section 1 Preliminaries | B4: Bill No. 1: Fixed Charge Items | H4: (Applicable to the whole of the Works)
A5: Section 1 Preliminaries | B5: Bill No. 1: Fixed Charge Items | H5: BILL NO. 1
A6: Section 1 Preliminaries | B6: Bill No. 1: Fixed Charge Items | G6: 8.3 | H6: FIXED CHARGE ITEMS
A7: Section 1 Preliminaries | B7: Bill No. 1: Fixed Charge Items | H7: PREAMBLE
A8: Section 1 Preliminaries | B8: Bill No. 1: Fixed Charge Items | H8: A detailed breakdown of the Preliminaries and General costs should be submitted with this tender
A9: Section 1 Preliminaries | B9: Bill No. 1: Fixed Charge Items | F9: A | G9: 8.3.1 | H9: Contractual requirements | I9: SUM | J9: 1 | K9: 500000 | L9: =J9*K9 -> 500000 | M9: 1 | N9: 1 | O9: 500000 | P9: =O9*M9 -> 500000 | Q9: =O9*N9 -> 500000
A10: Section 1 Preliminaries | B10: Bill No. 1: Fixed Charge Items | G10: 8.3.2.2 | H10: Facilities for Contractor | P10: =O10*M10 -> 0 | Q10: =O10*N10 -> 0
A11: Section 1 Preliminaries | B11: Bill No. 1: Fixed Charge Items | F11: B | G11: 8.3.2.2.a) | H11: Offices and storage sheds | I11: SUM | J11: 1 | K11: 30000 | L11: =J11*K11 -> 30000 | M11: 1 | N11: 1 | O11: 30000 | P11: =O11*M11 -> 30000 | Q11: =O11*N11 -> 30000
A12: Section 1 Preliminaries | B12: Bill No. 1: Fixed Charge Items | F12: C | G12: 8.3.2.2.b) | H12: Workshops | I12: SUM | J12: 1 | K12: 10000 | L12: =J12*K12 -> 10000 | M12: 1 | N12: 1 | O12: 10000 | P12: =O12*M12 -> 10000 | Q12: =O12*N12 -> 10000
A13: Section 1 Preliminaries | B13: Bill No. 1: Fixed Charge Items | F13: D | G13: 8.3.2.2.c) | H13: Laboratories. | I13: Sum | J13: 1 | K13: 10000 | L13: =K13*J13 -> 10000 | M13: 1 | N13: 1 | O13: 10000 | P13: =O13*M13 -> 10000 | Q13: =O13*N13 -> 10000
A14: Section 1 Preliminaries | B14: Bill No. 1: Fixed Charge Items | F14: E | G14: 8.3.2.2.d) | H14: Living accommodation. | I14: Sum | J14: 1 | K14: 20000 | L14: =K14*J14 -> 20000 | M14: 1 | N14: 1 | O14: 20000 | P14: =O14*M14 -> 20000 | Q14: =O14*N14 -> 20000
A15: Section 1 Preliminaries | B15: Bill No. 1: Fixed Charge Items | F15: F | G15: 8.3.2.2.e) | H15: Ablution and latrine facilities. | I15: Sum | J15: 1 | K15: 20000 | L15: =K15*J15 -> 20000 | M15: 1 | N15: 1 | O15: 20000 | P15: =O15*M15 -> 20000 | Q15: =O15*N15 -> 20000
A16: Section 1 Preliminaries | B16: Bill No. 1: Fixed Charge Items | F16: G | G16: 8.3.2.2.f) | H16: Tools and equipment | I16: SUM | J16: 1 | K16: 20000 | L16: =J16*K16 -> 20000 | M16: 1 | N16: 1 | O16: 20000 | P16: =O16*M16 -> 20000 | Q16: =O16*N16 -> 20000
A17: Section 1 Preliminaries | B17: Bill No. 1: Fixed Charge Items | F17: H | G17: 8.3.2.2.g) | H17: Water supplies, electric power, communications, dealing with water, and access | I17: SUM | J17: 1 | K17: 15000 | L17: =J17*K17 -> 15000 | M17: 1 | N17: 1 | O17: 15000 | P17: =O17*M17 -> 15000 | Q17: =O17*N17 -> 15000
A18: Section 1 Preliminaries | B18: Bill No. 1: Fixed Charge Items | F18: J | G18: 8.3.2.2.j) | H18: Plant. | I18: SUM | J18: 1 | K18: 25000 | L18: =K18*J18 -> 25000 | M18: 1 | N18: 1 | O18: 25000 | P18: =O18*M18 -> 25000 | Q18: =O18*N18 -> 25000
A19: Section 1 Preliminaries | B19: Bill No. 1: Fixed Charge Items | F19: K | H19: Medicals and inductions | I19: SUM | J19: 1 | K19: 20000 | L19: =K19*J19 -> 20000 | M19: 1 | N19: 1 | O19: 20000 | P19: =O19*M19 -> 20000 | Q19: =O19*N19 -> 20000
A20: Section 1 Preliminaries | B20: Bill No. 1: Fixed Charge Items | F20: L | H20: Fencing of laydown area | I20: SUM | J20: 1 | K20: 55933.13 | L20: =K20*J20 -> 55933.13 | M20: 1 | N20: 1 | O20: 55933.13 | P20: =O20*M20 -> 55933.13 | Q20: =O20*N20 -> 55933.13
A21: Section 1 Preliminaries | B21: Bill No. 1: Fixed Charge Items | F21: M | G21: 8.3.3 | H21: Other fixed charge obligations | I21: SUM | J21: 1 | K21: 5000 | L21: =J21*K21 -> 5000 | M21: 1 | N21: 1 | O21: 5000 | P21: =O21*M21 -> 5000 | Q21: =O21*N21 -> 5000
A22: Section 1 Preliminaries | B22: Bill No. 1: Fixed Charge Items | F22: N | G22: 8.3.4 | H22: Removal of site establishment | I22: SUM | J22: 1 | K22: 15000 | L22: =J22*K22 -> 15000 | M22: 1 | N22: 1 | O22: 15000 | P22: =O22*M22 -> 15000 | Q22: =O22*N22 -> 15000
A23: Section 1 Preliminaries | B23: Bill No. 2: Time Related Items | H23: SECTION NO. 1 | P23: =O23*M23 -> 0 | Q23: =O23*N23 -> 0
A24: Section 1 Preliminaries | B24: Bill No. 2: Time Related Items | G24: SANS 1200A | H24: PRELIMINARY AND GENERAL | P24: =O24*M24 -> 0 | Q24: =O24*N24 -> 0
A25: Section 1 Preliminaries | B25: Bill No. 2: Time Related Items | H25: (Applicable to the whole of the Works) | P25: =O25*M25 -> 0 | Q25: =O25*N25 -> 0
A26: Section 1 Preliminaries | B26: Bill No. 2: Time Related Items | H26: BILL NO. 2 | P26: =O26*M26 -> 0 | Q26: =O26*N26 -> 0
A27: Section 1 Preliminaries | B27: Bill No. 2: Time Related Items | G27: 8.4 | H27: TIME RELATED ITEMS | P27: =O27*M27 -> 0 | Q27: =O27*N27 -> 0
A28: Section 1 Preliminaries | B28: Bill No. 2: Time Related Items | H28: PREAMBLE | P28: =O28*M28 -> 0 | Q28: =O28*N28 -> 0
A29: Section 1 Preliminaries | B29: Bill No. 2: Time Related Items | H29: A detailed breakdown of the Preliminaries and General costs should be submitted with this tender | P29: =O29*M29 -> 0 | Q29: =O29*N29 -> 0
A30: Section 1 Preliminaries | B30: Bill No. 2: Time Related Items | F30: A | G30: 8.4.1 | H30: Contractual requirements | I30: SUM | J30: 1 | K30: 100000 | L30: =J30*K30 -> 100000 | M30: 1 | N30: 1 | O30: 100000 | P30: =O30*M30 -> 100000 | Q30: =O30*N30 -> 100000
A31: Section 1 Preliminaries | B31: Bill No. 2: Time Related Items | G31: 8.4.2 | H31: Operation and Maintenance of Facilities on Site, for Duration of Construction, (unless otherwise stated) | P31: =O31*M31 -> 0 | Q31: =O31*N31 -> 0
A32: Section 1 Preliminaries | B32: Bill No. 2: Time Related Items | G32: 8.4.2.2 | H32: Facilities for Contractor | P32: =O32*M32 -> 0 | Q32: =O32*N32 -> 0
A33: Section 1 Preliminaries | B33: Bill No. 2: Time Related Items | F33: B | G33: 8.4.2.2.a) | H33: Offices and storage sheds | I33: SUM | J33: 1 | K33: 30000 | L33: =J33*K33 -> 30000 | M33: 1 | N33: 1 | O33: 30000 | P33: =O33*M33 -> 30000 | Q33: =O33*N33 -> 30000
A34: Section 1 Preliminaries | B34: Bill No. 2: Time Related Items | F34: C | G34: 8.4.2.2.b) | H34: Workshops | I34: SUM | J34: 1 | K34: 15000 | L34: =J34*K34 -> 15000 | M34: 1 | N34: 1 | O34: 15000 | P34: =O34*M34 -> 15000 | Q34: =O34*N34 -> 15000
A35: Section 1 Preliminaries | B35: Bill No. 2: Time Related Items | F35: D | G35: 8.4.2.2.c) | H35: Laboratories | I35: SUM | J35: 1 | K35: 15000 | L35: =J35*K35 -> 15000 | M35: 1 | N35: 1 | O35: 15000 | P35: =O35*M35 -> 15000 | Q35: =O35*N35 -> 15000
A36: Section 1 Preliminaries | B36: Bill No. 2: Time Related Items | F36: E | G36: 8.4.2.2.d) | H36: Living accommodation | I36: SUM | J36: 1 | K36: 30000 | L36: =J36*K36 -> 30000 | M36: 1 | N36: 1 | O36: 30000 | P36: =O36*M36 -> 30000 | Q36: =O36*N36 -> 30000
A37: Section 1 Preliminaries | B37: Bill No. 2: Time Related Items | F37: F | G37: 8.4.2.2.e) | H37: Ablution and latrine facilities | I37: SUM | J37: 1 | K37: 30000 | L37: =J37*K37 -> 30000 | M37: 1 | N37: 1 | O37: 30000 | P37: =O37*M37 -> 30000 | Q37: =O37*N37 -> 30000
A38: Section 1 Preliminaries | B38: Bill No. 2: Time Related Items | F38: G | G38: 8.4.2.2.f) | H38: Tools and equipment | I38: SUM | J38: 1 | K38: 20000 | L38: =J38*K38 -> 20000 | M38: 1 | N38: 1 | O38: 20000 | P38: =O38*M38 -> 20000 | Q38: =O38*N38 -> 20000
A39: Section 1 Preliminaries | B39: Bill No. 2: Time Related Items | F39: H | G39: 8.4.2.2.g) | H39: Water supplies, electric power, communications, dealing with water, and access | I39: SUM | J39: 1 | K39: 20000 | L39: =J39*K39 -> 20000 | M39: 1 | N39: 1 | O39: 20000 | P39: =O39*M39 -> 20000 | Q39: =O39*N39 -> 20000
A40: Section 1 Preliminaries | B40: Bill No. 2: Time Related Items | F40: J | G40: 8.4.2.2.j) | H40: Plant | I40: SUM | J40: 1 | K40: 60000 | L40: =J40*K40 -> 60000 | M40: 1 | N40: 1 | O40: 60000 | P40: =O40*M40 -> 60000 | Q40: =O40*N40 -> 60000
A41: Section 1 Preliminaries | B41: Bill No. 2: Time Related Items | F41: K | G41: 8.4.3 | H41: Supervision for duration of construction | I41: SUM | J41: 1 | K41: 120000 | L41: =J41*K41 -> 120000 | M41: 1 | N41: 1 | O41: 120000 | P41: =O41*M41 -> 120000 | Q41: =O41*N41 -> 120000
A42: Section 1 Preliminaries | B42: Bill No. 2: Time Related Items | F42: L | G42: 8.4.4 | H42: Company and head office overhead costs for duration of the contract | I42: SUM | J42: 1 | K42: 24000 | L42: =J42*K42 -> 24000 | M42: 1 | N42: 1 | O42: 24000 | P42: =O42*M42 -> 24000 | Q42: =O42*N42 -> 24000
A43: Section 1 Preliminaries | B43: Bill No. 2: Time Related Items | F43: M | H43: Safety Compliance | I43: Sum | J43: 1 | K43: 200000 | L43: =K43*J43 -> 200000 | M43: 1 | N43: 1 | O43: 200000 | P43: =O43*M43 -> 200000 | Q43: =O43*N43 -> 200000
A44: Section 1 Preliminaries | B44: Bill No. 2: Time Related Items | F44: N | G44: 8.4.5 | H44: Other time related obligations | I44: SUM | J44: 1 | K44: 10000 | L44: =J44*K44 -> 10000 | M44: 1 | N44: 1 | O44: 10000 | P44: =O44*M44 -> 10000 | Q44: =O44*N44 -> 10000
A45: Section 1 Preliminaries | B45: Bill No. 2: Time Related Items | F45: P | G45: 8.4.5.1 | H45: Community Liason Officer's Salary | I45: SUM | J45: 1 | K45: 60000 | L45: =J45*K45 -> 60000 | M45: 1 | N45: 1 | O45: 60000 | P45: =O45*M45 -> 60000 | Q45: =O45*N45 -> 60000
A46: Section 1 Preliminaries | B46: Bill No. 2: Time Related Items | F46: Q | G46: 8.4.5.2 | H46: Security for the duration of the project | I46: SUM | J46: 1 | K46: 100000 | L46: =J46*K46 -> 100000 | M46: 1 | N46: 1 | O46: 100000 | P46: =O46*M46 -> 100000 | Q46: =O46*N46 -> 100000
A47: Section 2: Media Centre | B47: Bill No. 1: Earthworks | H47: SECTION NO. 2 | P47: =O47*M47 -> 0 | Q47: =O47*N47 -> 0
A48: Section 2: Media Centre | B48: Bill No. 1: Earthworks | H48: LEPHADIMISHA - MEDIA CENTRE | P48: =O48*M48 -> 0 | Q48: =O48*N48 -> 0
A49: Section 2: Media Centre | B49: Bill No. 1: Earthworks | H49: BILL NO. 1 | P49: =O49*M49 -> 0 | Q49: =O49*N49 -> 0
A50: Section 2: Media Centre | B50: Bill No. 1: Earthworks | G50: SANS 1200D | H50: EARTHWORKS | P50: =O50*M50 -> 0 | Q50: =O50*N50 -> 0
A51: Section 2: Media Centre | B51: Bill No. 1: Earthworks | H51: NOTES | P51: =O51*M51 -> 0 | Q51: =O51*N51 -> 0
A52: Section 2: Media Centre | B52: Bill No. 1: Earthworks | H52: For preambles see "Model Preambles for Trades 2017" | P52: =O52*M52 -> 0 | Q52: =O52*N52 -> 0
A53: Section 2: Media Centre | B53: Bill No. 1: Earthworks | H53: SUPPLEMENTARY PREAMBLES | P53: =O53*M53 -> 0 | Q53: =O53*N53 -> 0
A54: Section 2: Media Centre | B54: Bill No. 1: Earthworks | H54: Nature of ground | P54: =O54*M54 -> 0 | Q54: =O54*N54 -> 0
A55: Section 2: Media Centre | B55: Bill No. 1: Earthworks | H55: Descriptions of excavations shall be deemed to include all ground conditions classifiable as "earth", and where conditions of a more difficult character are indicated, these are separately measured. | P55: =O55*M55 -> 0 | Q55: =O55*N55 -> 0
A56: Section 2: Media Centre | B56: Bill No. 1: Earthworks | G56: 8.3 | H56: SCHEDULED ITEMS | P56: =O56*M56 -> 0 | Q56: =O56*N56 -> 0
A57: Section 2: Media Centre | B57: Bill No. 1: Earthworks | G57: 8.3.1 | H57: Site preparation | P57: =O57*M57 -> 0 | Q57: =O57*N57 -> 0
A58: Section 2: Media Centre | B58: Bill No. 1: Earthworks | F58: A | G58: 8.3.1.1 | H58: Rip and scarify in-situ 150mm layer free of organic material and compact to 93% Mod AASHTO density | I58: m2 | J58: 307 | K58: 25 | L58: =K58*J58 -> 7675 | M58: 307 | N58: 307 | O58: 25 | P58: =O58*M58 -> 7675 | Q58: =O58*N58 -> 7675
A59: Section 2: Media Centre | B59: Bill No. 1: Earthworks | F59: B | G59: 8.3.1.2 | H59: Remove topsoil to nominal depth 150mm, stockpile and maintain | I59: m2 | J59: =J58 -> 307 | K59: 65 | L59: =K59*J59 -> 19955 | M59: =M58 -> 307 | N59: =N58 -> 307 | O59: 65 | P59: =O59*M59 -> 19955 | Q59: =O59*N59 -> 19955
A60: Section 2: Media Centre | B60: Bill No. 1: Earthworks | H60: EXCAVATION, FILLING, ETC | P60: =O60*M60 -> 0 | Q60: =O60*N60 -> 0
A61: Section 2: Media Centre | B61: Bill No. 1: Earthworks | G61: 8.3.3 | H61: Restricted Excavation | P61: =O61*M61 -> 0 | Q61: =O61*N61 -> 0
A62: Section 2: Media Centre | B62: Bill No. 1: Earthworks | F62: C | G62: 8.3.3.a.1) | H62: Excavate for restricted footings in all materials | I62: m3 | J62: 112 | K62: 85 | L62: =J62*K62 -> 9520 | M62: 112 | N62: 112 | O62: 85 | P62: =O62*M62 -> 9520 | Q62: =O62*N62 -> 9520
A63: Section 2: Media Centre | B63: Bill No. 1: Earthworks | H63: Extra-over for | P63: =O63*M63 -> 0 | Q63: =O63*N63 -> 0
A64: Section 2: Media Centre | B64: Bill No. 1: Earthworks | F64: D | G64: 8.3.3.b.1) | H64: Intermediate excavation | I64: m3 | J64: =J62*0.1 -> 11.2 | K64: 95 | L64: =J64*K64 -> 1064 | M64: =M62*0.1 -> 11.2 | N64: =N62*0.1 -> 11.2 | O64: 95 | P64: =O64*M64 -> 1064 | Q64: =O64*N64 -> 1064
A65: Section 2: Media Centre | B65: Bill No. 1: Earthworks | F65: E | G65: 8.3.3.b.2) | H65: Hard rock excavation | I65: m3 | J65: =J62*0.05 -> 5.6 | K65: 350 | L65: =J65*K65 -> 1960 | M65: =M62*0.05 -> 5.6 | N65: =N62*0.05 -> 5.6 | O65: 350 | P65: =O65*M65 -> 1960 | Q65: =O65*N65 -> 1960
A66: Section 2: Media Centre | B66: Bill No. 1: Earthworks | G66: 8.3.4 | H66: Importing of Material | P66: =O66*M66 -> 0 | Q66: =O66*N66 -> 0
A67: Section 2: Media Centre | B67: Bill No. 1: Earthworks | G67: 8.3.4.a) | H67: Extra-over for importation of materials from commercial sources | P67: =O67*M67 -> 0 | Q67: =O67*N67 -> 0
A68: Section 2: Media Centre | B68: Bill No. 1: Earthworks | F68: F | H68: G5 material compacted in 150mm thick layers to 95% MOD AASHTO density at 1% to 2% optimum moisture content under footing | I68: m3 | J68: 41 | K68: 320 | L68: =K68*J68 -> 13120 | M68: 41 | N68: 41 | O68: 320 | P68: =O68*M68 -> 13120 | Q68: =O68*N68 -> 13120
A69: Section 2: Media Centre | B69: Bill No. 1: Earthworks | F69: G | H69: G5 Material in layers compacted to 95% Mod AASHTO density in layers not exceeding 150mm under surface bed | I69: m3 | J69: 99 | K69: 320 | L69: =K69*J69 -> 31680 | M69: 99 | N69: 99 | O69: 320 | P69: =O69*M69 -> 31680 | Q69: =O69*N69 -> 31680
A70: Section 2: Media Centre | B70: Bill No. 1: Earthworks | F70: H | G70: 8.3.6 | H70: Overhaul | P70: =O70*M70 -> 0 | Q70: =O70*N70 -> 0
A71: Section 2: Media Centre | B71: Bill No. 1: Earthworks | F71: J | G71: 8.3.6.b) | H71: Long overhaul in excess of 2km and within a 20km radius | I71: m3.km | J71: =J62*12 -> 1344 | K71: 8 | L71: =K71*J71 -> 10752 | M71: =M62*12 -> 1344 | N71: =N62*12 -> 1344 | O71: 8 | P71: =O71*M71 -> 10752 | Q71: =O71*N71 -> 10752
A72: Section 2: Media Centre | B72: Bill No. 1: Earthworks | H72: SOIL POISONING | P72: =O72*M72 -> 0 | Q72: =O72*N72 -> 0
A73: Section 2: Media Centre | B73: Bill No. 1: Earthworks | H73: Soil insecticide in accordance with SANS 5859 | P73: =O73*M73 -> 0 | Q73: =O73*N73 -> 0
A74: Section 2: Media Centre | B74: Bill No. 1: Earthworks | F74: K | H74: Under floors etc. including forming and poisoning shallow furrows against foundation walls etc., filling in furrows and ramming | I74: m2 | J74: 353 | K74: 35 | L74: =K74*J74 -> 12355 | M74: 353 | N74: 353 | O74: 35 | P74: =O74*M74 -> 12355 | Q74: =O74*N74 -> 12355
A75: Section 2: Media Centre | B75: Bill No. 2: Concrete (Structural) | H75: SECTION NO. 2 | P75: =O75*M75 -> 0 | Q75: =O75*N75 -> 0
A76: Section 2: Media Centre | B76: Bill No. 2: Concrete (Structural) | H76: =H48 -> LEPHADIMISHA - MEDIA CENTRE | P76: =O76*M76 -> 0 | Q76: =O76*N76 -> 0
A77: Section 2: Media Centre | B77: Bill No. 2: Concrete (Structural) | H77: BILL NO. 2 | P77: =O77*M77 -> 0 | Q77: =O77*N77 -> 0
A78: Section 2: Media Centre | B78: Bill No. 2: Concrete (Structural) | G78: SANS 1200G | H78: CONCRETE (STRUCTURAL) | P78: =O78*M78 -> 0 | Q78: =O78*N78 -> 0
A79: Section 2: Media Centre | B79: Bill No. 2: Concrete (Structural) | H79: NOTES | P79: =O79*M79 -> 0 | Q79: =O79*N79 -> 0
A80: Section 2: Media Centre | B80: Bill No. 2: Concrete (Structural) | H80: For preambles see "Model Preambles for Trades 2017" | P80: =O80*M80 -> 0 | Q80: =O80*N80 -> 0
A81: Section 2: Media Centre | B81: Bill No. 2: Concrete (Structural) | H81: SUPPLEMENTARY PREAMBLES | P81: =O81*M81 -> 0 | Q81: =O81*N81 -> 0
A82: Section 2: Media Centre | B82: Bill No. 2: Concrete (Structural) | H82: Cost of tests | P82: =O82*M82 -> 0 | Q82: =O82*N82 -> 0
A83: Section 2: Media Centre | B83: Bill No. 2: Concrete (Structural) | H83: The costs of making, storing and testing of concrete test cubes as required under clause 7 "Tests" of SANS 1200G shall include the cost of providing cube moulds necessary for the purpose, for testing costs and for submitting reports on the tests to the Supervisor. The testing shall be undertaken by an independent firm or institution nominated by the contractor to the approval of the Supervisor. (Test cubes are measured separately) | P83: =O83*M83 -> 0 | Q83: =O83*N83 -> 0
A84: Section 2: Media Centre | B84: Bill No. 2: Concrete (Structural) | H84: Formwork | P84: =O84*M84 -> 0 | Q84: =O84*N84 -> 0
A85: Section 2: Media Centre | B85: Bill No. 2: Concrete (Structural) | H85: Formwork to soffits of solids etc. shall be deemed to be slabs not exceeding 300mm thick unless otherwise described | P85: =O85*M85 -> 0 | Q85: =O85*N85 -> 0
A86: Section 2: Media Centre | B86: Bill No. 2: Concrete (Structural) | H86: Formwork to sides of bases, pile caps, ground beams, etc. will only be measured where it is prescribed by the engineer for design reasons. Formwork necessitated by irregularity or collapse of excavated faces will not be measured and the cost thereof shall be deemed to be included in the allowance for taking the risk of collapse of the sides of the excavations, provision for which is made in "Earthworks" | P86: =O86*M86 -> 0 | Q86: =O86*N86 -> 0
A87: Section 2: Media Centre | B87: Bill No. 2: Concrete (Structural) | H87: All H.D bolts, washers and nuts to be supplied by the contractor | P87: =O87*M87 -> 0 | Q87: =O87*N87 -> 0
A88: Section 2: Media Centre | B88: Bill No. 2: Concrete (Structural) | H88: Rates to include for sandblasting and galvanizing all bolts and metal work to applicable specification | P88: =O88*M88 -> 0 | Q88: =O88*N88 -> 0
A89: Section 2: Media Centre | B89: Bill No. 2: Concrete (Structural) | G89: 8.2 | H89: FORMWORK (PROVISIONAL) | P89: =O89*M89 -> 0 | Q89: =O89*N89 -> 0
A90: Section 2: Media Centre | B90: Bill No. 2: Concrete (Structural) | G90: 8.2.1 | H90: Rough formwork | P90: =O90*M90 -> 0 | Q90: =O90*N90 -> 0
A91: Section 2: Media Centre | B91: Bill No. 2: Concrete (Structural) | F91: A | H91: To sides footing | I91: m2 | J91: 67 | K91: 385 | L91: =J91*K91 -> 25795 | M91: 67 | N91: 67 | O91: 385 | P91: =O91*M91 -> 25795 | Q91: =O91*N91 -> 25795
A92: Section 2: Media Centre | B92: Bill No. 2: Concrete (Structural) | G92: 8.3 | H92: REINFORCEMENT (PROVISIONAL) | P92: =O92*M92 -> 0 | Q92: =O92*N92 -> 0
A93: Section 2: Media Centre | B93: Bill No. 2: Concrete (Structural) | G93: 8.3.1 | H93: Steel Bars in Structural Steel | P93: =O93*M93 -> 0 | Q93: =O93*N93 -> 0
A94: Section 2: Media Centre | B94: Bill No. 2: Concrete (Structural) | G94: 8.3.1 | H94: Steel Bars | P94: =O94*M94 -> 0 | Q94: =O94*N94 -> 0
A95: Section 2: Media Centre | B95: Bill No. 2: Concrete (Structural) | H95: High-tensile | P95: =O95*M95 -> 0 | Q95: =O95*N95 -> 0
A96: Section 2: Media Centre | B96: Bill No. 2: Concrete (Structural) | F96: B | H96: Various Bars | I96: t | J96: 0.539 | K96: 19500 | L96: =J96*K96 -> 10510.5 | M96: 0.539 | N96: 0.539 | O96: 19500 | P96: =O96*M96 -> 10510.5 | Q96: =O96*N96 -> 10510.5
A97: Section 2: Media Centre | B97: Bill No. 2: Concrete (Structural) | H97: Mild steel | P97: =O97*M97 -> 0 | Q97: =O97*N97 -> 0
A98: Section 2: Media Centre | B98: Bill No. 2: Concrete (Structural) | F98: C | H98: Various Bars | I98: t | J98: 0.12 | K98: 19500 | L98: =J98*K98 -> 2340 | M98: 0.12 | N98: 0.12 | O98: 19500 | P98: =O98*M98 -> 2340 | Q98: =O98*N98 -> 2340
A99: Section 2: Media Centre | B99: Bill No. 2: Concrete (Structural) | G99: 8.3.2 | H99: High-tensile welded mesh | P99: =O99*M99 -> 0 | Q99: =O99*N99 -> 0
A100: Section 2: Media Centre | B100: Bill No. 2: Concrete (Structural) | F100: D | H100: Ref 395 layer mesh in surface bed | I100: m2 | J100: 141 | K100: 145 | L100: =J100*K100 -> 20445 | M100: 141 | N100: 141 | O100: 145 | P100: =O100*M100 -> 20445 | Q100: =O100*N100 -> 20445
...

Sheet Trade Code
A1: PREFIX | B1: TRADE NAME | C1: TRADE CODE
A2: PRE- | B2: Preliminaries | C2: =A2&B2 -> PRE-Preliminaries
A3: EAR- | B3: Earthworks | C3: =A3&B3 -> EAR-Earthworks
A4: CFR- | B4: Concrete, Formwork & Reinforcement | C4: =A4&B4 -> CFR-Concrete, Formwork & Reinforcement
A5: PRC- | B5: Precast Concrete | C5: =A5&B5 -> PRC-Precast Concrete
A6: MAN- | B6: Masonry | C6: =A6&B6 -> MAN-Masonry
A7: WPR- | B7: Waterproofing | C7: =A7&B7 -> WPR-Waterproofing
A8: ROF- | B8: Roofing Coverings | C8: =A8&B8 -> ROF-Roofing Coverings
A9: CRJ- | B9: Carpentry and Joinery | C9: =A9&B9 -> CRJ-Carpentry and Joinery
A10: CPA- | B10: Ceilings, Partitions & Access Flooring | C10: =A10&B10 -> CPA-Ceilings, Partitions & Access Flooring
A11: FLR- | B11: Floor Coverings, Wall Linings, Etc | C11: =A11&B11 -> FLR-Floor Coverings, Wall Linings, Etc
A12: IRM- | B12: Ironmongery | C12: =A12&B12 -> IRM-Ironmongery
A13: STW- | B13: Structural Steelwork | C13: =A13&B13 -> STW-Structural Steelwork
... A23: EXT- | B23: External Work | C23: =A23&B23 -> EXT-External Work

Sheet Account Code
A1: Number | B1: Name | C1: Account Code
A2: 1001 - | B2: Sales/ Revenue | C2: =A2&B2 -> 1001 - Sales/ Revenue
A3: 1002 - | B3: Cash Deposit | C3: =A3&B3 -> 1002 - Cash Deposit
A4: 2000 - | B4: General | C4: =A4&B4 -> 2000 - General
A5: 2001 - | B5: Materials | C5: =A5&B5 -> 2001 - Materials
A6: 2002 - | B6: Labour | C6: =A6&B6 -> 2002 - Labour
A7: 2003 - | B7: Plant and Equipment | C7: =A7&B7 -> 2003 - Plant and Equipment
A8: 2004 - | B8: Tools | C8: =A8&B8 -> 2004 - Tools
A9: 2005 - | B9: Consumables | C9: =A9&B9 -> 2005 - Consumables
A10: 2006 - | B10: Inventory | C10: =A10&B10 -> 2006 - Inventory
A11: 2007 - | B11: Subcontractor | C11: =A11&B11 -> 2007 - Subcontractor
A12: 2008 - | B12: Other | C12: =A12&B12 -> 2008 - Other
A13: 3000 - | B13: General | C13: =A13&B13 -> 3000 - General
... A37: 4017 - | B37: Other | C37: =A37&B37 -> 4017 - Other

Sheet Specification Code
B1: concrete settings
G2: Quantity per m3 of Concrete | L2: Quantity for Bill Quantity
A3: Trade Code | B3: Concrete Name | C3: Concrete strength | D3: Cement Code | E3: Dand Code | F3: Stone Link | G3: Cement bags | H3: Sand cubes | I3: Stone cubes | J3: Rate/m3 | K3: BoQ Quantity | L3: Cement bags | M3: Sand cubes | N3: Stone cubes
A4: CFR-Concrete, Formwork & Reinforcement | B4: CONC_10 | C4: 10MPa Mix | D4: CFR01-CEM-42.5N | E4: CFR01-SAN-RIV | F4: CFR01-STO-19 | G4: 4.2 | H4: 0.75 | I4: 0.75 | J4: =G4*'Materials Code'!G$2+'Specification Code'!H4*'Materials Code'!G$4+'Specification Code'!I4*'Materials Code'!G$5 -> 1366.8 | K4: 10 | L4: =K4*H4 -> 7.5 | M4: =K4*H4 -> 7.5 | N4: =K4*I4 -> 7.5
A5: CFR-Concrete, Formwork & Reinforcement | B5: CONC_15 | C5: 15MPa Mix | D5: CFR01-CEM-42.5N | E5: CFR01-SAN-RIV | F5: CFR01-STO-19 | G5: 6.2 | H5: 0.7 | I5: 0.8 | J5: =G5*'Materials Code'!G$2+'Specification Code'!H5*'Materials Code'!G$4+'Specification Code'!I5*'Materials Code'!G$5 -> 1624.8 | K5: ='Output BoQ'!J107 -> 14 | L5: =K5*H5 -> 9.8 | M5: =K5*H5 -> 9.8 | N5: =K5*I5 -> 11.2
A6: CFR-Concrete, Formwork & Reinforcement | B6: CONC_20 | C6: 20MPa Mix | D6: CFR01-CEM-42.5N | E6: CFR01-SAN-RIV | F6: CFR01-STO-19 | G6: 7.5 | H6: 0.65 | I6: 0.85 | J6: =G6*'Materials Code'!G$2+'Specification Code'!H6*'Materials Code'!G$4+'Specification Code'!I6*'Materials Code'!G$5 -> 1792.5 | K6: 10 | L6: =K6*H6 -> 6.5 | M6: =K6*H6 -> 6.5 | N6: =K6*I6 -> 8.5
A7: CFR-Concrete, Formwork & Reinforcement | B7: CONC_25 | C7: 25MPa Mix | D7: CFR01-CEM-32.5R | E7: CFR01-SAN-RIV | F7: CFR01-STO-19 | G7: 8.2 | H7: 0.65 | I7: 0.85 | J7: =G7*'Materials Code'!G$2+'Specification Code'!H7*'Materials Code'!G$4+'Specification Code'!I7*'Materials Code'!G$5 -> 1882.8 | K7: 10 | L7: =K7*H7 -> 6.5 | M7: =K7*H7 -> 6.5 | N7: =K7*I7 -> 8.5
A8: CFR-Concrete, Formwork & Reinforcement | B8: CONC_30 | C8: 30MPa Mix | D8: CFR01-CEM-42.5N | E8: CFR01-SAN-RIV | F8: CFR01-STO-19 | G8: 9.8 | H8: 0.6 | I8: 0.9 | J8: =G8*'Materials Code'!G$2+'Specification Code'!H8*'Materials Code'!G$4+'Specification Code'!I8*'Materials Code'!G$5 -> 2089.2 | K8: 10 | L8: =K8*H8 -> 6 | M8: =K8*H8 -> 6 | N8: =K8*I8 -> 9

Sheet Materials Code
A1: Prefix | B1: Trade Code | C1: Material Code | D1: Item Code | E1: Material Variety | F1: Market Spec / Strength | G1: Market Rate | H1: Unit
A2: CFR - | B2: CFR-Concrete, Formwork & Reinforcement | C2: CEM-42.5N | D2: =A2&C2 -> CFR -CEM-42.5N | E2: Portland Cement | F2: 42.5N Structural | G2: 129 | H2: Bag
A3: CFR - | B3: CFR-Concrete, Formwork & Reinforcement | C3: CEM-52.5N | D3: =A3&C3 -> CFR -CEM-52.5N | E3: High Strength Cement | F3: 52.5N (for Columns/Slabs) | G3: 145 | H3: Bag
A4: CFR - | B4: CFR-Concrete, Formwork & Reinforcement | C4: SAN-RIV | D4: =A4&C4 -> CFR -SAN-RIV | E4: River Sand | F4: Sharp/Concreting Sand | G4: 550 | H4: m3
A5: CFR - | B5: CFR-Concrete, Formwork & Reinforcement | C5: STO-19 | D5: =A5&C5 -> CFR -STO-19 | E5: Concrete Stone | F5: 19mm Crushed Aggregate | G5: 550 | H5: m3
A6: CFR - | B6: CFR-Concrete, Formwork & Reinforcement | C6: STO-13 | D6: =A6&C6 -> CFR -STO-13 | E6: Concrete Stone | F6: 13.2mm (for Thin Sections) | H6: m3
A7: CFR - | B7: CFR-Concrete, Formwork & Reinforcement | C7: STO-9.5 | D7: =A7&C7 -> CFR -STO-9.5 | E7: Concrete Stone | F7: 9.5mm (for Rib & Block) | H7: m3
A8: CFR - | B8: CFR-Concrete, Formwork & Reinforcement | C8: CON-CUR | D8: =A8&C8 -> CFR -CON-CUR | E8: Curing Compound | F8: Prescribed Curing Liquid | H8: 25L
A9: CFR - | B9: CFR-Concrete, Formwork & Reinforcement | C9: CON-GRO-NS | D9: =A9&C9 -> CFR -CON-GRO-NS | E9: Non-Shrink Grout | F9: For Column Bases/Beds | H9: 25kg
A10: CFR - | B10: CFR-Concrete, Formwork & Reinforcement | C10: FRM-PLY-21 | D10: =A10&C10 -> CFR -FRM-PLY-21 | E10: Shutterboard | F10: 21mm FHP Brown Film | H10: Sheet
A11: CFR - | B11: CFR-Concrete, Formwork & Reinforcement | C11: FRM-TIM-S5 | D11: =A11&C11 -> CFR -FRM-TIM-S5 | E11: Shutter Timber | F11: 38 x 114mm S5 Structural | H11: Lm
A12: CFR - | B12: CFR-Concrete, Formwork & Reinforcement | C12: FRM-OIL-RE | D12: =A12&C12 -> CFR -FRM-OIL-RE | E12: Release Agent | F12: Shutter Oil (Chemical) | H12: 20L
A13: CFR - | B13: CFR-Concrete, Formwork & Reinforcement | C13: FRM-TIE-RD | D13: =A13&C13 -> CFR -FRM-TIE-RD | E13: Tie Rods | F13: High Tensile (for Walls/Columns) | H13: m
A14: CFR - | B14: CFR-Concrete, Formwork & Reinforcement | C14: FRM-TIE-CO | D14: =A14&C14 -> CFR -FRM-TIE-CO | E14: Ferrules/Cones | F14: Plastic Sleeves for Tie Rods | H14: Each
A15: CFR - | B15: CFR-Concrete, Formwork & Reinforcement | C15: FRM-CHM-ST | D15: =A15&C15 -> CFR -FRM-CHM-ST | E15: Chamfer Strip | F15: 20mm x 20mm PVC | H15: Lm
A16: CFR - | B16: CFR-Concrete, Formwork & Reinforcement | C16: Y-REBAR-VAR | D16: =A16&C16 -> CFR -Y-REBAR-VAR | E16: High Yield Steel | F16: 450MPa (Y10, Y12, Y16, Y20) | H16: Ton/ Kg
A17: CFR - | B17: CFR-Concrete, Formwork & Reinforcement | C17: R-REBAR-VAR | D17: =A17&C17 -> CFR -R-REBAR-VAR | E17: Mild Steel Rods | F17: 250MPa (R6, R8, R10) | H17: Ton/ Kg
... A22: CFR - | B22: CFR-Concrete, Formwork & Reinforcement | C22: BIND-WIRE | D22: =A22&C22 -> CFR -BIND-WIRE | E22: Binding Wire | F22: 1.6mm Annealed | H22: 50kg
A23: MAN - | B23: MAN-Masonry | C23: NFP-230 | D23: =A23&C23 -> MAN -NFP-230 | E23: Common Clay Brick | F23: 222x106x73mm (Double skin) | H23: 1000
A24: MAN - | B24: MAN-Masonry | C24: NFP-115 | D24: =A24&C24 -> MAN -NFP-115 | E24: Common Clay Brick | F24: 222x106x73mm (Single skin) | H24: 1000
A25: MAN - | B25: MAN-Masonry | C25: FBX-230 | D25: =A25&C25 -> MAN -FBX-230 | E25: Face Brick Extra | F25: 222x106x73mm (High Grade) | H25: 1000
A26: MAN - | B26: MAN-Masonry | C26: CEM-STD | D26: =A26&C26 -> MAN -CEM-STD | E26: Cement Brick | F26: Standard 7MPa | H26: 1000
A27: MAN - | B27: MAN-Masonry | C27: BLOCK-M140 | D27: =A27&C27 -> MAN -BLOCK-M140 | E27: Hollow Block | F27: 390x140x190mm | H27: Each
A28: MAN - | B28: MAN-Masonry | C28: BLOCK-M90 | D28: =A28&C28 -> MAN -BLOCK-M90 | E28: Hollow Block | F28: 390x90x190mm | H28: Each
A29: MAN - | B29: MAN-Masonry | C29: BLOCK-U140 | D29: =A29&C29 -> MAN -BLOCK-U140 | E29: U-Block Lintel | F29: For 140mm Block walls | H29: Each
A30: MAN - | B30: MAN-Masonry | C30: CEM-PORT-42.4N | D30: =A30&C30 -> MAN -CEM-PORT-42.4N | E30: Portland Cement | F30: 42.5N Strength | H30: Bag
A31: MAN - | B31: MAN-Masonry | C31: BUILD-LIME | D31: =A31&C31 -> MAN -BUILD-LIME | E31: Building Lime | F31: Hydrated Mortar Lime | H31: Bag
A32: MAN - | B32: MAN-Masonry | C32: BUILD-SAND | D32: =A32&C32 -> MAN -BUILD-SAND | E32: Building Sand | F32: Screened Pit/River Sand | H32: m3
A33: MAN - | B33: MAN-Masonry | C33: MOR-PIGM | D33: =A33&C33 -> MAN -MOR-PIGM | E33: Mortar Pigment | F33: Black/Red (for Facebrick) | H33: kg
A34: MAN - | B34: MAN-Masonry | C34: BRK-FOR-75 | D34: =A34&C34 -> MAN -BRK-FOR-75 | E34: Brickforce | F34: 75mm Galvanized | H34: 20m
A35: MAN - | B35: MAN-Masonry | C35: BRK-FOR-150 | D35: =A35&C35 -> MAN -BRK-FOR-150 | E35: Brickforce | F35: 150mm Galvanized | H35: 20m
A36: MAN - | B36: MAN-Masonry | C36: HOOP-32 | D36: =A36&C36 -> MAN -HOOP-32 | E36: Hoop Iron Tie | F36: 32 x 1.6mm (Roof/Wall Ties) | H36: 30m
A37: MAN - | B37: MAN-Masonry | C37: WALL-TIE-C | D37: =A37&C37 -> MAN -WALL-TIE-C | E37: Wall Tie | F37: Crimped Wire (5 per m2) | H37: Each
A38: MAN - | B38: MAN-Masonry | C38: Y10-REBAR | D38: =A38&C38 -> MAN -Y10-REBAR | E38: High Yield Steel | F38: 10mm Bars (for Arches/Piers) | H38: Ton
... A156: FLR - | B156: FLR-Floor Coverings, Wall Linings, Etc | C156: ACC-EDG-STL | D156: =A156&C156 -> FLR -ACC-EDG-STL | E156: Edge Strips | F156: Aluminum Transition/Nosing | H156: Each
A157: IRM - | B157: IRM-Ironmongery | C157: HNG-BUTT | E157: Butt Hinges | F157: 100mm Stainless Steel (Pair) | H157: Pair
A158: IRM - | B158: IRM-Ironmongery | C158: HNG-SPR | E158: Floor Spring | F158: Double Action Hydraulic | H158: Set
A159: IRM - | B159: IRM-Ironmongery | C159: HND-LEV | E159: Lever Handle | F159: S/S Return-to-door (Standard) | H159: Set
A160: IRM - | B160: IRM-Ironmongery | C160: HND-PUL | E160: Pull Handle | F160: 300mm D-Handle (Alternative) | H160: Each
A161: IRM - | B161: IRM-Ironmongery | C161: HK-HAT | E161: Hat & Coat Hook | F161: Single Prong S/S | H161: Each
A162: IRM - | B162: IRM-Ironmongery | C162: LCK-CYL-3L | D162: =A162&C162 -> IRM -LCK-CYL-3L | E162: Cylinder Lock | F162: 3-Lever Standard | H162: Each
A163: IRM - | B163: IRM-Ironmongery | C163: LCK-CYL-EUR | D163: =A163&C163 -> IRM -LCK-CYL-EUR | E163: Euro Profile | F163: 5-Pin Security Cylinder (Alt) | H163: Each
A164: IRM - | B164: IRM-Ironmongery | C164: LCK-MAS-KEY | D164: =A164&C164 -> IRM -LCK-MAS-KEY | E164: Master Key System | F164: Multi-Level Access Coding | H164: Per Door
A165: IRM - | B165: IRM-Ironmongery | C165: LCK-ENS-SUITE | D165: =A165&C165 -> IRM -LCK-ENS-SUITE | E165: En Suite Locks | F165: Keyed Alike (per 10 units) | H165: Set
A166: IRM - | B166: IRM-Ironmongery | C166: CRD-SET | D166: =A166&C166 -> IRM -CRD-SET | E166: Cording Set | F166: Emergency Pull / Sash Cord | H166: Set
A167: IRM - | B167: IRM-Ironmongery | C167: SLD-GR-INT | D167: =A167&C167 -> IRM -SLD-GR-INT | E167: Sliding Gear | F167: 900mm Internal Door Track | H167: Set
A168: IRM - | B168: IRM-Ironmongery | C168: SLD-GR-HVY | D168: =A168&C168 -> IRM -SLD-GR-HVY | E168: Heavy Duty Gear | F168: Industrial/Cavity Slider (Alt) | H168: Set
A169: IRM - | B169: IRM-Ironmongery | C169: RAL-TOW | D169: =A169&C169 -> IRM -RAL-TOW | E169: Towel Rail | F169: 600mm Stainless Steel | H169: Each
A170: IRM - | B170: IRM-Ironmongery | C170: RAL-GRB | D170: =A170&C170 -> IRM -RAL-GRB | E170: Grab Rail | F170: 300mm Paraplegic S/S | H170: Each
A171: IRM - | B171: IRM-Ironmongery | C171: FIT-LOK-MET | D171: =A171&C171 -> IRM -FIT-LOK-MET | E171: Metal Locker | F171: Single Tier Steel Unit | H171: Each
A172: IRM - | B172: IRM-Ironmongery | C172: FIT-LOK-TIM | D172: =A172&C172 -> IRM -FIT-LOK-TIM | E172: Timber Locker | F172: Melamine / Veneer Unit (Alt) | H172: Each
A173: IRM - | B173: IRM-Ironmongery | C173: FIT-WRT-BRD | D173: =A173&C173 -> IRM -FIT-WRT-BRD | E173: Writing Board | F173: 1200x900mm Whiteboard/Cork | H173: Each
... A389: EXT - | B389: EXT-External Work | C389: SUN-DRA-GUL | D389: =A389&C389 -> EXT -SUN-DRA-GUL | E389: Yard Gully | F389: PVC 110mm with Grating | H389: Each
